Flock/__init__.py
Flock/flock.py
Flock/Themes/custom_style.css
Flock/Themes/dark_theme.css
Flock/Themes/flock_icon.png
Flock/Themes/fun_theme.css
Flock/Themes/light_theme.css
Flock/Themes/std_blue.css
Flock/Themes/std_firebrick.css
Flock/Themes/std_green.css
Flock/Themes/std_orange.css
Flock/Themes/std_purple.css
Flock/docs/Flock-HowTo.html
Flock/src/OScheckLooper.py
Flock/src/__init__.py
Flock/src/argChecker.py
Flock/src/assetMonitor.py
Flock/src/settings.py
Flock/src/themeSelector.py
Flock/src/converter/__init__.py
Flock/src/converter/markdown2html.py
Flock/src/converter/markdown_extensions.py
Flock/src/copier/__init__.py
Flock/src/copier/fileCopy.py
Flock/src/docs/__init__.py
Flock/src/docs/showDocs.py
Flock/src/navigator/__init__.py
Flock/src/navigator/dirNaviV2.py
Flock/src/stubber/Stubber2.py
Flock/src/stubber/__init__.py
Flock-Windows/__init__.py
Flock-Windows/flock.py
Flock-Windows/Themes/custom_style.css
Flock-Windows/Themes/dark_theme.css
Flock-Windows/Themes/flock_icon.png
Flock-Windows/Themes/fun_theme.css
Flock-Windows/Themes/light_theme.css
Flock-Windows/Themes/std_blue.css
Flock-Windows/Themes/std_firebrick.css
Flock-Windows/Themes/std_green.css
Flock-Windows/Themes/std_orange.css
Flock-Windows/Themes/std_purple.css
Flock-Windows/docs/Flock-HowTo.html
Flock-Windows/docs/firstUse
Flock-Windows/src/OScheckLooper.py
Flock-Windows/src/__init__.py
Flock-Windows/src/argChecker.py
Flock-Windows/src/assetMonitor.py
Flock-Windows/src/settings.py
Flock-Windows/src/themeSelector.py
Flock-Windows/src/__pycache__/OScheckLooper.cpython-37.pyc
Flock-Windows/src/__pycache__/__init__.cpython-37.pyc
Flock-Windows/src/__pycache__/argChecker.cpython-37.pyc
Flock-Windows/src/__pycache__/assetMonitor.cpython-37.pyc
Flock-Windows/src/__pycache__/settings.cpython-37.pyc
Flock-Windows/src/__pycache__/themeSelector.cpython-37.pyc
Flock-Windows/src/converter/__init__.py
Flock-Windows/src/converter/markdown2html.py
Flock-Windows/src/converter/markdown_extensions.py
Flock_SSG-0.1.0.dist-info/LICENSE.txt
Flock_SSG-0.1.0.dist-info/METADATA
Flock_SSG-0.1.0.dist-info/WHEEL
Flock_SSG-0.1.0.dist-info/top_level.txt
Flock_SSG-0.1.0.dist-info/RECORD
