Metadata-Version: 2.1
Name: Flock-SSG
Version: 0.1.0
Summary: A static site generator
Home-page: https://github.com/rdall96/Flock_SSG
Author: Derek Connelly, Ricky Dall‘Armellina, Dan Levy, Lukas Mallory
Author-email: conneld@sunyit.edu
License: UNKNOWN
Platform: UNKNOWN
Classifier: Programming Language :: Python :: 3
Classifier: License :: OSI Approved :: MIT License
Classifier: Operating System :: OS Independent
